Metadata-Version: 2.4
Name: array-api-extra
Version: 0.9.0
Summary: Extra array functions built on top of the array API standard.
Project-URL: Homepage, https://github.com/data-apis/array-api-extra
Project-URL: Bug Tracker, https://github.com/data-apis/array-api-extra/issues
Project-URL: Changelog, https://github.com/data-apis/array-api-extra/releases
Author-email: Lucas Colley <lucas.colley8@gmail.com>
License: MIT License
License-File: LICENSE
Classifier: Intended Audience :: Developers
Classifier: License :: OSI Approved :: MIT License
Classifier: Operating System :: OS Independent
Classifier: Programming Language :: Python
Classifier: Programming Language :: Python :: 3
Classifier: Programming Language :: Python :: 3 :: Only
Classifier: Programming Language :: Python :: 3.10
Classifier: Programming Language :: Python :: 3.11
Classifier: Programming Language :: Python :: 3.12
Classifier: Programming Language :: Python :: 3.13
Classifier: Programming Language :: Python :: Free Threading :: 3 - Stable
Classifier: Typing :: Typed
Requires-Python: >=3.10
Requires-Dist: array-api-compat<2,>=1.12.0
